mc/__init__.py
mc/exceptions.py
mc/formatters.py
mc/util.py
mc/validators.py
mc.py-3.0.3.dist-info/LICENSE
mc.py-3.0.3.dist-info/METADATA
mc.py-3.0.3.dist-info/WHEEL
mc.py-3.0.3.dist-info/top_level.txt
mc.py-3.0.3.dist-info/RECORD
