Metadata-Version: 2.1
Name: mc.py
Version: 3.0.3
Summary: String generator based on Markov process
Home-page: https://github.com/jieggii/mc.py
Author: jieggii
Author-email: jieggii@protonmail.com
License: MIT
Project-URL: Documentation, https://github.com/jieggii/mc.py/blob/master/docs/README.md
Project-URL: Source, https://github.com/jieggii/mc.py
Project-URL: Tracker, https://github.com/jieggii/mc.py/issues
Platform: UNKNOWN
Requires-Python: >=3
